anevia_testrail/__init__.py
anevia_testrail/_case.py
anevia_testrail/_config.py
anevia_testrail/_constants.py
anevia_testrail/_sender.py
anevia_testrail/plugin.py
anevia_testrail/pytestrail.py
anevia_testrail-1.0.0.dist-info/LICENSE
anevia_testrail-1.0.0.dist-info/METADATA
anevia_testrail-1.0.0.dist-info/WHEEL
anevia_testrail-1.0.0.dist-info/entry_points.txt
anevia_testrail-1.0.0.dist-info/top_level.txt
anevia_testrail-1.0.0.dist-info/RECORD
