Metadata-Version: 2.1
Name: anevia-testrail
Version: 1.0.0
Summary: Pytest plugin for interaction with TestRail
Home-page: https://gitlab.anevia.com/neniolaafolabi/anevia-testrail
Author: Noah ENIOLA AFOLABI
Author-email: neniolaafolabi@anevia.com
License: MIT License
Platform: UNKNOWN
Requires-Python: >=3.5
Requires-Dist: pytest (>=3.8.0)
Requires-Dist: testrail-api (>=1.8.0)
